cat2/__init__.py
cat2/cli.py
cat2-0.3.1.dist-info/METADATA
cat2-0.3.1.dist-info/RECORD
cat2-0.3.1.dist-info/WHEEL
cat2-0.3.1.dist-info/entry_points.txt
cat2-0.3.1.dist-info/top_level.txt
