Metadata-Version: 2.1
Name: cat2
Version: 0.3.1
Summary: Print file contents like a boss
Home-page: https://github.com/arrrlo/cat2
Author: Ivan Arar
Author-email: ivan.arar@gmail.com
License: MIT
Project-URL: Source, https://github.com/arrrlo/cat2
Keywords: cat,print,file,contents
Platform: UNKNOWN
Classifier: Development Status :: 4 - Beta
Classifier: Intended Audience :: Developers
Classifier: Topic :: Software Development :: Build Tools
Classifier: License :: OSI Approved :: MIT License
Classifier: Programming Language :: Python :: 3
Requires-Dist: click (~=6.7)
Requires-Dist: colorama (~=0.3)
